winter/__init__.py
winter/core/__init__.py
winter/core/annotation_decorator.py
winter/core/annotations.py
winter/core/application.py
winter/core/component.py
winter/core/component_method.py
winter/core/component_method_argument.py
winter/core/docstring.py
winter/core/injection.py
winter/core/json/__init__.py
winter/core/json/decoder.py
winter/core/json/encoder.py
winter/core/json/undefined.py
winter/core/module_discovery.py
winter/core/utils/__init__.py
winter/core/utils/beautify_string.py
winter/core/utils/nested_types.py
winter/core/utils/positive_integer.py
winter/core/utils/typing.py
winter/data/__init__.py
winter/data/exceptions.py
winter/data/pagination/__init__.py
winter/data/pagination/page.py
winter/data/pagination/page_position.py
winter/data/pagination/sort.py
winter/data/repository.py
winter/messaging/__init__.py
winter/messaging/event.py
winter/messaging/event_dispacher.py
winter/messaging/event_handler.py
winter/messaging/event_publisher.py
winter/messaging/event_subscription.py
winter/messaging/event_subscription_registry.py
winter/messaging/simple_event_publisher.py
winter/web/__init__.py
winter/web/argument_resolver.py
winter/web/autodiscovery.py
winter/web/default_response_status.py
winter/web/exception_handlers.py
winter/web/exceptions/__init__.py
winter/web/exceptions/exception_handler_generator.py
winter/web/exceptions/exception_mapper.py
winter/web/exceptions/exceptions.py
winter/web/exceptions/handlers.py
winter/web/exceptions/problem.py
winter/web/exceptions/problem_annotation.py
winter/web/exceptions/problem_handling.py
winter/web/exceptions/problem_handling_info.py
winter/web/exceptions/raises.py
winter/web/interceptor.py
winter/web/media_type.py
winter/web/output_processor.py
winter/web/pagination/__init__.py
winter/web/pagination/check_sort.py
winter/web/pagination/limits.py
winter/web/pagination/order_by.py
winter/web/pagination/order_by_annotation.py
winter/web/pagination/page_position_argument_resolver.py
winter-31.0.2.dist-info/LICENSE
winter-31.0.2.dist-info/METADATA
winter-31.0.2.dist-info/WHEEL
winter-31.0.2.dist-info/RECORD
