Metadata-Version: 2.3
Name: winter
Version: 31.0.2
Summary: Web Framework with focus on python typing, dataclasses and modular design
Author: Alexander Egorov
Author-email: mofr@zond.org
Requires-Python: >=3.11,<4.0
Classifier: Development Status :: 3 - Alpha
Classifier: Environment :: Web Environment
Classifier: Framework :: Django
Classifier: Framework :: Django :: 4
Classifier: Intended Audience :: Developers
Classifier: License :: OSI Approved :: MIT License
Classifier: Operating System :: OS Independent
Classifier: Programming Language :: Python
Classifier: Programming Language :: Python :: 3
Classifier: Programming Language :: Python :: 3.11
Classifier: Programming Language :: Python :: 3.12
Classifier: Programming Language :: Python :: 3.13
Classifier: Topic :: Software Development :: Libraries :: Application Frameworks
Requires-Dist: Django (>=4.2,<5)
Requires-Dist: SQLAlchemy (>=1.4,<2)
Requires-Dist: StrEnum (>=0.4.8,<0.5.0)
Requires-Dist: docstring-parser (>=0.1)
Requires-Dist: furl (>=2.0.0,<3)
Requires-Dist: httpx (>=0.24.1,<0.28)
Requires-Dist: injector (>=0.15.0,<1)
Requires-Dist: openapi-pydantic (>=0.5.0,<0.6)
Requires-Dist: openapi-spec-validator (>=0.5.7,<1)
Requires-Dist: pydantic (>=1.10,<2)
Requires-Dist: python-dateutil (>=2.8.2,<3.0.0)
Requires-Dist: redis (>=6.2.0,<7.0.0)
Requires-Dist: typing-extensions (>=4.8,<5.0)
Requires-Dist: uritemplate (==4.2.0)
Project-URL: Homepage, https://github.com/WinterFramework/winter
